8_bit_adder/tester.v
// Actual test code for the adder module
module tester
		#(parameter N=1)	// Placeholder value, the working one is declared in the testbench file
		(
		CLK,	// Clock signal
		ENB,	// Enable signal
		MODO,	// Mode select
		A,	// A input number
		B,	// B input number
		RCI,	// Ripple counter input
		Q,	// Output number output
		RCO);	// Ripple counter output

// For the tester, inputs and outputs are swapped respect to the DUT,
// thus allowing to interact and manipulate the other module
// Input declaration
input [N-1:0] [3:0] Q;
input RCO;

// Output declaration
output CLK, ENB;
output [1:0] MODO;
output RCI;
output [N-1:0] [3:0] A;
output [N-1:0] [3:0] B;

// Wires and regs are inverted as well
reg CLK, ENB;
reg [1:0] MODO;
reg RCI;
reg [N-1:0] [3:0] A;
reg [N-1:0] [3:0] B;

wire [N-1:0] [3:0] Q;
wire RCO;

// Half frequency definition, in terms of time units
parameter h_freq=1;

// CLK signal setup
always begin
	#h_freq CLK = !CLK;
end

// Testing starts after this line
initial begin

	#0	CLK	=	0;
	#0	ENB	=	0;
	#0	MODO	=	2'b00;
	#0	A	=	8'b0;
	#0	B	=	8'b0;
	#0	RCI	=	2'b00;
	#5	ENB	=	1;
	#25	MODO	=	2'b10; // Resta
	#0	A	=	8'b01100100;
	#0	B	=	8'b01100000;
	#25	MODO	=	2'b01; // Suma
	#0	A	=	8'b00001000;
	#0	B	=	8'b00010000;
	#25	MODO	=	2'b00; // Mantener
	#0	A	=	8'b00001001;
	#0	B	=	8'b00000111;
	#25	MODO	=	2'b11; // Reset
	#0	A	=	8'b00110010;
	#0	B	=	8'b00011010;
	#25	$finish;
end


endmodule

32_bit_adder/adder.v
// Behavioural description of 4 bit adder
module adder4b (
		CLK,	// Clock signal
		ENB,	// Enable signal
		MODO,	// Mode select
		A,	// A input number
		B,	// B input number
		RCI,	// Ripple counter input
		Q,	// Output number output
		RCO);	// Ripple counter output

// Input declaration
input CLK, ENB, RCI;
input [1:0] MODO;
input [3:0] A, B;

// Output declaration
output [3:0] Q;
output RCO;

// Role declaration of input and outputs
wire CLK, ENB, RCI;
wire [1:0] MODO;
wire [3:0] A, B;

reg [3:0] Q;
reg RCO;

// Concurrent detection of positive edge of clock and enable signal
always @ (posedge CLK && ENB == 1)
begin
	// Actions selected in mode signal take place
	// The ripple counter input is taken into account here and
	// the RCO is assigned as the MSB of the computed vector for
	// each operation
	// The substraction mode assumes that the data it gets comes
	// in two's complement form
	case (MODO)
		2'b00 : {RCO, Q} <= {RCO, Q};
		2'b01 : {RCO, Q} <= A + B + RCI;
		2'b10 : {RCO, Q} <= A - B + RCI;
		2'b11 : {RCO, Q} <= 5'b00000;
		default {RCO, Q} <= 5'b00000;
	endcase
end

// Behavior when enable is 0
always @ (ENB == 0)
begin
	// The first condition only applies when starting
	// circuit for the first time, it sets the output
	// ports to 0 so that they're not undefined.
	// The second one happens when enable is set to 0
	// after having produced an output before, and
	// only keeps the output ports on hold
	if (Q === 4'bx) begin
		Q = 4'b0;
		RCO = 0;
	end else begin
		Q = Q;
		RCO = RCO;
	end
end
endmodule

// Module for 4*n bit adder, it parametrizes adder4n
module adder4bn
		#(parameter N=1)		// Placeholder value, the working one is declared in the testbench file
		(
		input	CLK, ENB,		// CLK, ENB and MODO signals are shared
		input	[1:0] MODO,		// throughout all 4 bit adders.
		input	RCI, 
		input	[N-1:0] [3:0] A, B,	// These two dimensional arrays allow
		output	[N-1:0] [3:0] Q,	// to input and output several 4 bit
		output	RCO			// lenght signals to the module
		);
	// With the inputs and outputs declared, only two internal
	// arrays remains to be created, these will allow to link
	// the ripple counters leaving only two of them available to
	// be used
	wire iRC [N:0];		// Internal ripple counter array, the lenght is
				// greater than the rest of variables because
				// it allows the later loop to assign all the
				// ripple counter links autimatically, all with
				// one vector for correlation.
	assign iRC[0] = RCI;	// RCI is assinged as input to the first bit of iRC
	assign RCO = iRC[N];	// The last bit of iRC is assigned as output RCO

	genvar i;		// Temporary module instance index


	// Module generation
	generate
	// The actual loop goes from zero to N-1
	for (i = 0; i < N; i = i + 1) 
	begin
		// The module instancing goes as follows
		adder4b A0 (CLK, ENB, MODO, A[i], B[i], iRC[i], Q[i], iRC[i+1]);
	end
	endgenerate
endmodule

8_bit_adder/testbench.v
`include "adder.v"
`include "tester.v"

// Adder testbench
module adder_tb;
// First, the working variable for parameter N is declared
// this tells how many 4 bit adders are generated
parameter N = 2;
// reg elsewhere and this file only connects them
wire CLK, ENB;			// Inputs
wire [1:0] MODO;
wire RCI;	
wire [N-1:0] [3:0] A;
wire [N-1:0] [3:0] B;
wire RCO;		// Outputs
wire [N-1:0] [3:0] Q;

// Monitoring code
initial begin
	$dumpfile("adder_output.vcd");
	$dumpvars(-1);
	$monitor($time,,
		"CLK = %b    ENB = %b    MODO = %b    A = %b    B = %b    RCI = %b",  CLK, ENB, MODO, A, B, RCI,,
		"	Q = %b    RCO = %b",  Q, RCO);
end


// Instance creation for DUT and tester modules
adder4bn #(.N(N))
	A0 (
	.CLK (CLK),
	.ENB (ENB),
	.MODO (MODO),
	.A (A),
	.B (B),
	.RCI (RCI),
	.Q (Q),
	.RCO (RCO)
);

tester #(.N(N))
	P0 (
	.CLK (CLK),
	.ENB (ENB),
	.MODO (MODO),
	.A (A),
	.B (B),
	.RCI (RCI),
	.Q (Q),
	.RCO (RCO)
);

endmodule

8_bit_adder/8_bit_adder_wave_output.vcd
$date
	Sun Apr 16 20:30:16 2023
$end
$version
	Icarus Verilog
$end
$timescale
	1s
$end
$scope module adder_tb $end
$var wire 1 ! RCO $end
$var wire 1 " RCI $end
$var wire 8 # Q [7:0] $end
$var wire 2 $ MODO [1:0] $end
$var wire 1 % ENB $end
$var wire 1 & CLK $end
$var wire 8 ' B [7:0] $end
$var wire 8 ( A [7:0] $end
$scope module A0 $end
$var wire 1 ! RCO $end
$var wire 1 " RCI $end
$var wire 8 ) Q [7:0] $end
$var wire 2 * MODO [1:0] $end
$var wire 1 % ENB $end
$var wire 1 & CLK $end
$var wire 8 + B [7:0] $end
$var wire 8 , A [7:0] $end
$scope begin genblk1[0] $end
$scope module A0 $end
$var wire 4 - A [3:0] $end
$var wire 4 . B [3:0] $end
$var wire 1 / RCI $end
$var wire 2 0 MODO [1:0] $end
$var wire 1 % ENB $end
$var wire 1 & CLK $end
$var reg 4 1 Q [3:0] $end
$var reg 1 2 RCO $end
$upscope $end
$upscope $end
$scope begin genblk1[1] $end
$scope module A0 $end
$var wire 4 3 A [3:0] $end
$var wire 4 4 B [3:0] $end
$var wire 1 2 RCI $end
$var wire 2 5 MODO [1:0] $end
$var wire 1 % ENB $end
$var wire 1 & CLK $end
$var reg 4 6 Q [3:0] $end
$var reg 1 7 RCO $end
$upscope $end
$upscope $end
$upscope $end
$scope module P0 $end
$var wire 8 8 Q [7:0] $end
$var wire 1 ! RCO $end
$var reg 8 9 A [7:0] $end
$var reg 8 : B [7:0] $end
$var reg 1 & CLK $end
$var reg 1 % ENB $end
$var reg 2 ; MODO [1:0] $end
$var reg 1 " RCI $end
$upscope $end
$upscope $end
$enddefinitions $end
#0
$dumpvars
b0 ;
b0 :
b0 9
b0 8
07
b0 6
b0 5
b0 4
b0 3
02
b0 1
b0 0
0/
b0 .
b0 -
b0 ,
b0 +
b0 *
b0 )
b0 (
b0 '
0&
0%
b0 $
b0 #
0"
0!
$end
#1
1&
#2
0&
#3
1&
#4
0&
#5
1&
1%
#6
0&
#7
1&
#8
0&
#9
1&
#10
0&
#11
1&
#12
0&
#13
1&
#14
0&
#15
1&
#16
0&
#17
1&
#18
0&
#19
1&
#20
0&
#21
1&
#22
0&
#23
1&
#24
0&
#25
1&
#26
0&
#27
1&
#28
0&
#29
1&
#30
b110 4
b1100000 '
b1100000 +
b1100000 :
b110 3
b100 -
b1100100 (
b1100100 ,
b1100100 9
0&
b10 $
b10 *
b10 0
b10 5
b10 ;
#31
b100 #
b100 )
b100 8
b100 1
1&
#32
0&
#33
1&
#34
0&
#35
1&
#36
0&
#37
1&
#38
0&
#39
1&
#40
0&
#41
1&
#42
0&
#43
1&
#44
0&
#45
1&
#46
0&
#47
1&
#48
0&
#49
1&
#50
0&
#51
1&
#52
0&
#53
1&
#54
0&
#55
b11000100 #
b11000100 )
b11000100 8
b1100 6
b1 4
b10000 '
b10000 +
b10000 :
b0 3
b1000 -
b1000 (
b1000 ,
b1000 9
1&
b1 $
b1 *
b1 0
b1 5
b1 ;
#56
0&
#57
b1 6
b11000 #
b11000 )
b11000 8
b1000 1
1&
#58
0&
#59
1&
#60
0&
#61
1&
#62
0&
#63
1&
#64
0&
#65
1&
#66
0&
#67
1&
#68
0&
#69
1&
#70
0&
#71
1&
#72
0&
#73
1&
#74
0&
#75
1&
#76
0&
#77
1&
#78
0&
#79
1&
#80
b0 4
b111 .
b111 '
b111 +
b111 :
b1001 -
b1001 (
b1001 ,
b1001 9
0&
b0 $
b0 *
b0 0
b0 5
b0 ;
#81
1&
#82
0&
#83
1&
#84
0&
#85
1&
#86
0&
#87
1&
#88
0&
#89
1&
#90
0&
#91
1&
#92
0&
#93
1&
#94
0&
#95
1&
#96
0&
#97
1&
#98
0&
#99
1&
#100
0&
#101
1&
#102
0&
#103
1&
#104
0&
#105
b0 6
b0 #
b0 )
b0 8
b0 1
b1 4
b1010 .
b11010 '
b11010 +
b11010 :
b11 3
b10 -
b110010 (
b110010 ,
b110010 9
1&
b11 $
b11 *
b11 0
b11 5
b11 ;
