4_bit_adder/tester.v
// Actual test code for the adder module
module tester
		#(parameter N=1)	// Placeholder value, the working one is declared in the testbench file
		(
		CLK,	// Clock signal
		ENB,	// Enable signal
		MODO,	// Mode select
		A,	// A input number
		B,	// B input number
		RCI,	// Ripple counter input
		Q,	// Output number output
		RCO);	// Ripple counter output

// For the tester, inputs and outputs are swapped respect to the DUT,
// thus allowing to interact and manipulate the other module
// Input declaration
input [N-1:0] [3:0] Q;
input RCO;

// Output declaration
output CLK, ENB;
output [1:0] MODO;
output RCI;
output [N-1:0] [3:0] A;
output [N-1:0] [3:0] B;

// Wires and regs are inverted as well
reg CLK, ENB;
reg [1:0] MODO;
reg RCI;
reg [N-1:0] [3:0] A;
reg [N-1:0] [3:0] B;

wire [N-1:0] [3:0] Q;
wire RCO;

// Half frequency definition, in terms of time units
parameter h_freq=1;

// CLK signal setup
always begin
	#h_freq CLK = !CLK;
end

// Testing starts after this line
initial begin

	#0	CLK	=	0;
		ENB	=	0;
		MODO	=	2'b00;
		A	=	8'b0;
		B	=	8'b0;
		RCI	=	2'b00;
	#5	ENB	=	1;
		MODO	=	2'b11;
	#10	MODO	=	2'b10; // Resta
		A	=	4'b0110;
		B	=	4'b0010;
	#10	A	=	4'b0101;
		B	=	4'b0101;
	#10	A	=	4'b0010;
		B	=	4'b1000;
	#10	MODO	=	2'b11; // Setea a 0 
	#10	MODO	=	2'b01; // SumaS
		A	=	4'b0110;
		B	=	4'b0101;
	#10	A	=	4'b1000;
		B	=	4'b0100;
	#10	A	=	4'b1111;
		B	=	4'b0001;
	#10	MODO	=	2'b00; // Mantener
		A	=	4'b0101;
		B	=	4'b0010;
	#10	MODO	=	2'b11; // Reset
		A	=	4'b1111;
		B	=	4'b0000;
	#10	RCI	=	1;
	#10	MODO	=	2'b11; // Setea a 0
	#10	MODO	=	2'b10; // Resta
		A	=	4'b0110;
		B	=	4'b0010;
	#10	A	=	4'b0101;
		B	=	4'b0101;
	#10	A	=	4'b0010;
		B	=	4'b1000;
	#10	MODO	=	2'b11; // Setea a 0
	#10	MODO	=	2'b01; // Suma
		A	=	4'b0110;
		B	=	4'b0101;
	#10	A	=	4'b1000;
		B	=	4'b0100;
	#10	A	=	4'b1111;
		B	=	4'b0001;
	#10	MODO	=	2'b00; // Mantener
		A	=	4'b0101;
		B	=	4'b0010;
	#10	MODO	=	2'b01; // Reset
		A	=	4'b1111;
		B	=	4'b0000;
	#10	ENB	=	0;
		RCI	=	0;
	#10	MODO	=	2'b11; // Setea a 0
		MODO	=	2'b10; // Resta
		A	=	4'b0110;
		B	=	4'b0010;
	#10	A	=	4'b0101;
		B	=	4'b0101;
	#10	A	=	4'b0010;
		B	=	4'b1000;
	#10	MODO	=	2'b11; // Setea a 0
	#10	MODO	=	2'b01; // Suma
		A	=	4'b0110;
		B	=	4'b0101;
	#10	A	=	4'b1000;
		B	=	4'b0100;
	#10	A	=	4'b1111;
		B	=	4'b0001;
	#10	MODO	=	2'b00; // Mantener
		A	=	4'b0101;
		B	=	4'b0010;
	#10	MODO	=	2'b11; // Reset
		A	=	4'b1111;
		B	=	4'b0000;
	#10	RCI	=	1;
	#10	MODO	=	2'b11; // Setea a 0
	#10	MODO	=	2'b10; // Resta
		A	=	4'b0110;
		B	=	4'b0010;
	#10	A	=	4'b0101;
		B	=	4'b0101;
	#10	A	=	4'b0010;
		B	=	4'b1000;
	#10	MODO	=	2'b11; // Setea a 0
	#10	MODO	=	2'b01; // Suma
		A	=	4'b0110;
		B	=	4'b0101;
	#10	A	=	4'b1000;
		B	=	4'b0100;
	#10	A	=	4'b1111;
		B	=	4'b0001;
	#10	MODO	=	2'b00; // Mantener
		A	=	4'b0101;
		B	=	4'b0010;
	#10	MODO	=	2'b11; // Reset
		A	=	4'b1111;
		B	=	4'b0000;
	#10	$finish;
end


endmodule

32_bit_adder/adder.v
// Behavioural description of 4 bit adder
module adder4b (
		CLK,	// Clock signal
		ENB,	// Enable signal
		MODO,	// Mode select
		A,	// A input number
		B,	// B input number
		RCI,	// Ripple counter input
		Q,	// Output number output
		RCO);	// Ripple counter output

// Input declaration
input CLK, ENB, RCI;
input [1:0] MODO;
input [3:0] A, B;

// Output declaration
output [3:0] Q;
output RCO;

// Role declaration of input and outputs
wire CLK, ENB, RCI;
wire [1:0] MODO;
wire [3:0] A, B;

reg [3:0] Q;
reg RCO;

// Concurrent detection of positive edge of clock and enable signal
always @ (posedge CLK && ENB == 1)
begin
	// Actions selected in mode signal take place
	// The ripple counter input is taken into account here and
	// the RCO is assigned as the MSB of the computed vector for
	// each operation
	// The substraction mode assumes that the data it gets comes
	// in two's complement form
	case (MODO)
		2'b00 : {RCO, Q} <= {RCO, Q};
		2'b01 : {RCO, Q} <= A + B + RCI;
		2'b10 : {RCO, Q} <= A - B + RCI;
		2'b11 : {RCO, Q} <= 5'b00000;
		default {RCO, Q} <= 5'b00000;
	endcase
end

// Behavior when enable is 0
always @ (ENB == 0)
begin
	// The first condition only applies when starting
	// circuit for the first time, it sets the output
	// ports to 0 so that they're not undefined.
	// The second one happens when enable is set to 0
	// after having produced an output before, and
	// only keeps the output ports on hold
	if (Q === 4'bx) begin
		Q = 4'b0;
		RCO = 0;
	end else begin
		Q = Q;
		RCO = RCO;
	end
end
endmodule

// Module for 4*n bit adder, it parametrizes adder4n
module adder4bn
		#(parameter N=1)		// Placeholder value, the working one is declared in the testbench file
		(
		input	CLK, ENB,		// CLK, ENB and MODO signals are shared
		input	[1:0] MODO,		// throughout all 4 bit adders.
		input	RCI, 
		input	[N-1:0] [3:0] A, B,	// These two dimensional arrays allow
		output	[N-1:0] [3:0] Q,	// to input and output several 4 bit
		output	RCO			// lenght signals to the module
		);
	// With the inputs and outputs declared, only two internal
	// arrays remains to be created, these will allow to link
	// the ripple counters leaving only two of them available to
	// be used
	wire iRC [N:0];		// Internal ripple counter array, the lenght is
				// greater than the rest of variables because
				// it allows the later loop to assign all the
				// ripple counter links autimatically, all with
				// one vector for correlation.
	assign iRC[0] = RCI;	// RCI is assinged as input to the first bit of iRC
	assign RCO = iRC[N];	// The last bit of iRC is assigned as output RCO

	genvar i;		// Temporary module instance index


	// Module generation
	generate
	// The actual loop goes from zero to N-1
	for (i = 0; i < N; i = i + 1) 
	begin
		// The module instancing goes as follows
		adder4b A0 (CLK, ENB, MODO, A[i], B[i], iRC[i], Q[i], iRC[i+1]);
	end
	endgenerate
endmodule

4_bit_adder/testbench.v
`include "adder.v"
`include "tester.v"

// Adder testbench
module adder_tb;
// First, the working variable for parameter N is declared
// this tells how many 4 bit adders are generated
parameter N = 1;
// reg elsewhere and this file only connects them
wire CLK, ENB;			// Inputs
wire [1:0] MODO;
wire RCI;	
wire [N-1:0] [3:0] A;
wire [N-1:0] [3:0] B;
wire RCO;		// Outputs
wire [N-1:0] [3:0] Q;

// Monitoring code
initial begin
	$dumpfile("adder_output.vcd");
	$dumpvars(-1);
	$monitor($time,,
		"CLK = %b    ENB = %b    MODO = %b    A = %b    B = %b    RCI = %b",  CLK, ENB, MODO, A, B, RCI,,
		"	Q = %b    RCO = %b",  Q, RCO);
end


// Instance creation for DUT and tester modules
adder4bn #(.N(N))
	A0 (
	.CLK (CLK),
	.ENB (ENB),
	.MODO (MODO),
	.A (A),
	.B (B),
	.RCI (RCI),
	.Q (Q),
	.RCO (RCO)
);

tester #(.N(N))
	P0 (
	.CLK (CLK),
	.ENB (ENB),
	.MODO (MODO),
	.A (A),
	.B (B),
	.RCI (RCI),
	.Q (Q),
	.RCO (RCO)
);

endmodule

4_bit_adder/4_bit_adder_wave_output.vcd
$date
	Sun Apr 16 20:30:16 2023
$end
$version
	Icarus Verilog
$end
$timescale
	1s
$end
$scope module adder_tb $end
$var wire 1 ! RCO $end
$var wire 1 " RCI $end
$var wire 4 # Q [3:0] $end
$var wire 2 $ MODO [1:0] $end
$var wire 1 % ENB $end
$var wire 1 & CLK $end
$var wire 4 ' B [3:0] $end
$var wire 4 ( A [3:0] $end
$scope module A0 $end
$var wire 1 ! RCO $end
$var wire 1 " RCI $end
$var wire 4 ) Q [3:0] $end
$var wire 2 * MODO [1:0] $end
$var wire 1 % ENB $end
$var wire 1 & CLK $end
$var wire 4 + B [3:0] $end
$var wire 4 , A [3:0] $end
$scope begin genblk1[0] $end
$scope module A0 $end
$var wire 4 - A [3:0] $end
$var wire 4 . B [3:0] $end
$var wire 1 / RCI $end
$var wire 2 0 MODO [1:0] $end
$var wire 1 % ENB $end
$var wire 1 & CLK $end
$var reg 4 1 Q [3:0] $end
$var reg 1 2 RCO $end
$upscope $end
$upscope $end
$upscope $end
$scope module P0 $end
$var wire 4 3 Q [3:0] $end
$var wire 1 ! RCO $end
$var reg 4 4 A [3:0] $end
$var reg 4 5 B [3:0] $end
$var reg 1 & CLK $end
$var reg 1 % ENB $end
$var reg 2 6 MODO [1:0] $end
$var reg 1 " RCI $end
$upscope $end
$upscope $end
$enddefinitions $end
#0
$dumpvars
b0 6
b0 5
b0 4
b0 3
02
b0 1
b0 0
0/
b0 .
b0 -
b0 ,
b0 +
b0 *
b0 )
b0 (
b0 '
0&
0%
b0 $
b0 #
0"
0!
$end
#1
1&
#2
0&
#3
1&
#4
0&
#5
1&
b11 $
b11 *
b11 0
b11 6
1%
#6
0&
#7
1&
#8
0&
#9
1&
#10
0&
#11
1&
#12
0&
#13
1&
#14
0&
#15
b100 #
b100 )
b100 1
b100 3
b10 .
b110 -
1&
b10 '
b10 +
b10 5
b110 (
b110 ,
b110 4
b10 $
b10 *
b10 0
b10 6
#16
0&
#17
1&
#18
0&
#19
1&
#20
0&
#21
1&
#22
0&
#23
1&
#24
0&
#25
b0 #
b0 )
b0 1
b0 3
b101 .
b101 -
1&
b101 '
b101 +
b101 5
b101 (
b101 ,
b101 4
#26
0&
#27
1&
#28
0&
#29
1&
#30
0&
#31
1&
#32
0&
#33
1&
#34
0&
#35
1!
12
b1010 #
b1010 )
b1010 1
b1010 3
b1000 .
b10 -
1&
b1000 '
b1000 +
b1000 5
b10 (
b10 ,
b10 4
#36
0&
#37
1&
#38
0&
#39
1&
#40
0&
#41
1&
#42
0&
#43
1&
#44
0&
#45
0!
02
b0 #
b0 )
b0 1
b0 3
1&
b11 $
b11 *
b11 0
b11 6
#46
0&
#47
1&
#48
0&
#49
1&
#50
0&
#51
1&
#52
0&
#53
1&
#54
0&
#55
b1011 #
b1011 )
b1011 1
b1011 3
b101 .
b110 -
1&
b101 '
b101 +
b101 5
b110 (
b110 ,
b110 4
b1 $
b1 *
b1 0
b1 6
#56
0&
#57
1&
#58
0&
#59
1&
#60
0&
#61
1&
#62
0&
#63
1&
#64
0&
#65
b1100 #
b1100 )
b1100 1
b1100 3
b100 .
b1000 -
1&
b100 '
b100 +
b100 5
b1000 (
b1000 ,
b1000 4
#66
0&
#67
1&
#68
0&
#69
1&
#70
0&
#71
1&
#72
0&
#73
1&
#74
0&
#75
1!
12
b0 #
b0 )
b0 1
b0 3
b1 .
b1111 -
1&
b1 '
b1 +
b1 5
b1111 (
b1111 ,
b1111 4
#76
0&
#77
1&
#78
0&
#79
1&
#80
0&
#81
1&
#82
0&
#83
1&
#84
0&
#85
b10 .
b101 -
1&
b10 '
b10 +
b10 5
b101 (
b101 ,
b101 4
b0 $
b0 *
b0 0
b0 6
#86
0&
#87
1&
#88
0&
#89
1&
#90
0&
#91
1&
#92
0&
#93
1&
#94
0&
#95
0!
02
b0 .
b1111 -
1&
b0 '
b0 +
b0 5
b1111 (
b1111 ,
b1111 4
b11 $
b11 *
b11 0
b11 6
#96
0&
#97
1&
#98
0&
#99
1&
#100
0&
#101
1&
#102
0&
#103
1&
#104
0&
#105
1&
1/
1"
#106
0&
#107
1&
#108
0&
#109
1&
#110
0&
#111
1&
#112
0&
#113
1&
#114
0&
#115
1&
#116
0&
#117
1&
#118
0&
#119
1&
#120
0&
#121
1&
#122
0&
#123
1&
#124
0&
#125
b101 #
b101 )
b101 1
b101 3
b10 .
b110 -
1&
b10 '
b10 +
b10 5
b110 (
b110 ,
b110 4
b10 $
b10 *
b10 0
b10 6
#126
0&
#127
1&
#128
0&
#129
1&
#130
0&
#131
1&
#132
0&
#133
1&
#134
0&
#135
b1 #
b1 )
b1 1
b1 3
b101 .
b101 -
1&
b101 '
b101 +
b101 5
b101 (
b101 ,
b101 4
#136
0&
#137
1&
#138
0&
#139
1&
#140
0&
#141
1&
#142
0&
#143
1&
#144
0&
#145
1!
12
b1011 #
b1011 )
b1011 1
b1011 3
b1000 .
b10 -
1&
b1000 '
b1000 +
b1000 5
b10 (
b10 ,
b10 4
#146
0&
#147
1&
#148
0&
#149
1&
#150
0&
#151
1&
#152
0&
#153
1&
#154
0&
#155
0!
02
b0 #
b0 )
b0 1
b0 3
1&
b11 $
b11 *
b11 0
b11 6
#156
0&
#157
1&
#158
0&
#159
1&
#160
0&
#161
1&
#162
0&
#163
1&
#164
0&
#165
b1100 #
b1100 )
b1100 1
b1100 3
b101 .
b110 -
1&
b101 '
b101 +
b101 5
b110 (
b110 ,
b110 4
b1 $
b1 *
b1 0
b1 6
#166
0&
#167
1&
#168
0&
#169
1&
#170
0&
#171
1&
#172
0&
#173
1&
#174
0&
#175
b1101 #
b1101 )
b1101 1
b1101 3
b100 .
b1000 -
1&
b100 '
b100 +
b100 5
b1000 (
b1000 ,
b1000 4
#176
0&
#177
1&
#178
0&
#179
1&
#180
0&
#181
1&
#182
0&
#183
1&
#184
0&
#185
1!
12
b1 #
b1 )
b1 1
b1 3
b1 .
b1111 -
1&
b1 '
b1 +
b1 5
b1111 (
b1111 ,
b1111 4
#186
0&
#187
1&
#188
0&
#189
1&
#190
0&
#191
1&
#192
0&
#193
1&
#194
0&
#195
b10 .
b101 -
1&
b10 '
b10 +
b10 5
b101 (
b101 ,
b101 4
b0 $
b0 *
b0 0
b0 6
#196
0&
#197
1&
#198
0&
#199
1&
#200
0&
#201
1&
#202
0&
#203
1&
#204
0&
#205
b0 #
b0 )
b0 1
b0 3
b0 .
b1111 -
1&
b0 '
b0 +
b0 5
b1111 (
b1111 ,
b1111 4
b1 $
b1 *
b1 0
b1 6
#206
0&
#207
1&
#208
0&
#209
1&
#210
0&
#211
1&
#212
0&
#213
1&
#214
0&
#215
1&
0/
0"
0%
#216
0&
#217
1&
#218
0&
#219
1&
#220
0&
#221
1&
#222
0&
#223
1&
#224
0&
#225
b10 .
b110 -
1&
b10 '
b10 +
b10 5
b110 (
b110 ,
b110 4
b10 $
b10 *
b10 0
b10 6
#226
0&
#227
1&
#228
0&
#229
1&
#230
0&
#231
1&
#232
0&
#233
1&
#234
0&
#235
b101 .
b101 -
1&
b101 '
b101 +
b101 5
b101 (
b101 ,
b101 4
#236
0&
#237
1&
#238
0&
#239
1&
#240
0&
#241
1&
#242
0&
#243
1&
#244
0&
#245
b1000 .
b10 -
1&
b1000 '
b1000 +
b1000 5
b10 (
b10 ,
b10 4
#246
0&
#247
1&
#248
0&
#249
1&
#250
0&
#251
1&
#252
0&
#253
1&
#254
0&
#255
1&
b11 $
b11 *
b11 0
b11 6
#256
0&
#257
1&
#258
0&
#259
1&
#260
0&
#261
1&
#262
0&
#263
1&
#264
0&
#265
b101 .
b110 -
1&
b101 '
b101 +
b101 5
b110 (
b110 ,
b110 4
b1 $
b1 *
b1 0
b1 6
#266
0&
#267
1&
#268
0&
#269
1&
#270
0&
#271
1&
#272
0&
#273
1&
#274
0&
#275
b100 .
b1000 -
1&
b100 '
b100 +
b100 5
b1000 (
b1000 ,
b1000 4
#276
0&
#277
1&
#278
0&
#279
1&
#280
0&
#281
1&
#282
0&
#283
1&
#284
0&
#285
b1 .
b1111 -
1&
b1 '
b1 +
b1 5
b1111 (
b1111 ,
b1111 4
#286
0&
#287
1&
#288
0&
#289
1&
#290
0&
#291
1&
#292
0&
#293
1&
#294
0&
#295
b10 .
b101 -
1&
b10 '
b10 +
b10 5
b101 (
b101 ,
b101 4
b0 $
b0 *
b0 0
b0 6
#296
0&
#297
1&
#298
0&
#299
1&
#300
0&
#301
1&
#302
0&
#303
1&
#304
0&
#305
b0 .
b1111 -
1&
b0 '
b0 +
b0 5
b1111 (
b1111 ,
b1111 4
b11 $
b11 *
b11 0
b11 6
#306
0&
#307
1&
#308
0&
#309
1&
#310
0&
#311
1&
#312
0&
#313
1&
#314
0&
#315
1&
1/
1"
#316
0&
#317
1&
#318
0&
#319
1&
#320
0&
#321
1&
#322
0&
#323
1&
#324
0&
#325
1&
#326
0&
#327
1&
#328
0&
#329
1&
#330
0&
#331
1&
#332
0&
#333
1&
#334
0&
#335
b10 .
b110 -
1&
b10 '
b10 +
b10 5
b110 (
b110 ,
b110 4
b10 $
b10 *
b10 0
b10 6
#336
0&
#337
1&
#338
0&
#339
1&
#340
0&
#341
1&
#342
0&
#343
1&
#344
0&
#345
b101 .
b101 -
1&
b101 '
b101 +
b101 5
b101 (
b101 ,
b101 4
#346
0&
#347
1&
#348
0&
#349
1&
#350
0&
#351
1&
#352
0&
#353
1&
#354
0&
#355
b1000 .
b10 -
1&
b1000 '
b1000 +
b1000 5
b10 (
b10 ,
b10 4
#356
0&
#357
1&
#358
0&
#359
1&
#360
0&
#361
1&
#362
0&
#363
1&
#364
0&
#365
1&
b11 $
b11 *
b11 0
b11 6
#366
0&
#367
1&
#368
0&
#369
1&
#370
0&
#371
1&
#372
0&
#373
1&
#374
0&
#375
b101 .
b110 -
1&
b101 '
b101 +
b101 5
b110 (
b110 ,
b110 4
b1 $
b1 *
b1 0
b1 6
#376
0&
#377
1&
#378
0&
#379
1&
#380
0&
#381
1&
#382
0&
#383
1&
#384
0&
#385
b100 .
b1000 -
1&
b100 '
b100 +
b100 5
b1000 (
b1000 ,
b1000 4
#386
0&
#387
1&
#388
0&
#389
1&
#390
0&
#391
1&
#392
0&
#393
1&
#394
0&
#395
b1 .
b1111 -
1&
b1 '
b1 +
b1 5
b1111 (
b1111 ,
b1111 4
#396
0&
#397
1&
#398
0&
#399
1&
#400
0&
#401
1&
#402
0&
#403
1&
#404
0&
#405
b10 .
b101 -
1&
b10 '
b10 +
b10 5
b101 (
b101 ,
b101 4
b0 $
b0 *
b0 0
b0 6
#406
0&
#407
1&
#408
0&
#409
1&
#410
0&
#411
1&
#412
0&
#413
1&
#414
0&
#415
b0 .
b1111 -
1&
b0 '
b0 +
b0 5
b1111 (
b1111 ,
b1111 4
b11 $
b11 *
b11 0
b11 6
